[
  {
    "apn": "304-78-386",
    "address": "3674 E Palmer St",
    "city": "Gilbert",
    "state": "AZ",
    "zip": "85298",
    "legal_description": "Lot 46, SEVILLE PARCEL 3, according to the plat of record in the office of the County Recorder of Maricopa County, Arizona, recorded in Book 554 of Maps, Page 19; Affidavit of Correction recorded in Document No. 2001-0849180",
    "current_owner": "POPHAM CHRISTOPHER / ASHLEY",
    "type": "residential",
    "subdivision": "Seville Parcel 3",
    "assessor_url": "https://mcassessor.maricopa.gov/mcs/?q=30478386&mod=pd",
    "instrument_numbers": [
      "19780100001",
      "19950100001",
      "19990100001",
      "20010093192",
      "20010849180",
      "20020100001",
      "20020100002",
      "20050100001",
      "20060100001",
      "20130183449",
      "20130183450",
      "20210057846",
      "20210057847",
      "20210075858",
      "20240100001"
    ]
  },
  {
    "apn": "304-77-689",
    "address": "2715 E Palmer St",
    "city": "Gilbert",
    "state": "AZ",
    "zip": "85298",
    "legal_description": "Lot 348, SHAMROCK ESTATES PHASE 2A, according to the plat of record in the office of the County Recorder of Maricopa County, Arizona, recorded in Book 799 of Maps, Page 38",
    "current_owner": "HOGUE JASON / MICHELE",
    "type": "residential",
    "subdivision": "Shamrock Estates Phase 2A",
    "assessor_url": "https://mcassessor.maricopa.gov/mcs/?q=30477689&mod=pd",
    "instrument_numbers": [
      "20150516729",
      "20150516730"
    ]
  },
  {
    "apn": "304-78-409",
    "address": "TRACT A, SEVILLE PARCEL 3",
    "city": "Gilbert",
    "state": "AZ",
    "zip": "85295",
    "legal_description": "TRACT A, SEVILLE PARCEL 3, according to the plat of record in the office of the County Recorder of Maricopa County, Arizona, recorded in Book 554 of Maps, Page 19; Affidavit of Correction recorded in Document No. 2001-0849180",
    "current_owner": "SEVILLE HOMEOWNERS ASSOCIATION",
    "type": "subdivision_common",
    "subdivision": "Seville Parcel 3",
    "assessor_url": "https://mcassessor.maricopa.gov/mcs/?q=30478409&mod=pd",
    "instrument_numbers": [
      "20010093192",
      "20010849180"
    ]
  },
  {
    "apn": "304-78-374",
    "address": "6265 S Twilight Ct",
    "city": "Gilbert",
    "state": "AZ",
    "zip": "85298",
    "legal_description": "Lot 52, SEVILLE PARCEL 3, according to the plat of record in the office of the County Recorder of Maricopa County, Arizona, recorded in Book 554 of Maps, Page 19 and Affidavit of Correction recorded in Document No. 2001-0849180",
    "current_owner": "WARNER KAMA",
    "type": "residential",
    "subdivision": "Seville Parcel 3",
    "assessor_url": "https://mcassessor.maricopa.gov/mcs/?q=30478374&mod=pd",
    "instrument_numbers": [
      "20010093192",
      "20130087108",
      "20130087109",
      "20190100001"
    ]
  },
  {
    "apn": "304-78-383",
    "address": "3702 E Palmer St",
    "city": "Gilbert",
    "state": "AZ",
    "zip": "85297",
    "legal_description": "Lot 61, SEVILLE PARCEL 3, according to the plat of record in the office of the County Recorder of Maricopa County, Arizona, recorded in Book 554 of Maps, Page 19, and Affidavit of Correction recorded in Instrument No. 2001-0849180, and in Instrument No. 2001-0984501",
    "current_owner": "LOWRY AMY E",
    "type": "residential",
    "subdivision": "Seville Parcel 3",
    "assessor_url": "https://mcassessor.maricopa.gov/mcs/?q=30478383&mod=pd",
    "instrument_numbers": [
      "20010093192",
      "20070834753",
      "20070834755",
      "20090100001"
    ]
  },
  {
    "apn": "304-78-367",
    "address": "3671 E Palmer St",
    "city": "Gilbert",
    "state": "AZ",
    "zip": "85298",
    "legal_description": "Lot 45, SEVILLE PARCEL 3, according to the plat of record in the office of the County Recorder of Maricopa County, Arizona, recorded in Book 554 of Maps, Page 19; Affidavit of Correction recorded in Document No. 2001-0849180",
    "current_owner": "PHOENIX VACATION HOUSES LLC",
    "type": "residential",
    "subdivision": "Seville Parcel 3",
    "assessor_url": "https://mcassessor.maricopa.gov/mcs/?q=30478367&mod=pd",
    "instrument_numbers": [
      "20200620456",
      "20200620457",
      "20230100000",
      "20220100001"
    ]
  },
  {
    "apn": "999-01-362",
    "address": "3650 E Palmer St",
    "city": "Gilbert",
    "state": "AZ",
    "zip": "85298",
    "legal_description": "Lot 44, SEVILLE PARCEL 3, according to the plat of record in the office of the County Recorder of Maricopa County, Arizona, recorded in Book 554 of Maps, Page 19; Affidavit of Correction recorded in Document No. 2001-0849180",
    "current_owner": "CHEN DAVID JAMES",
    "type": "residential",
    "subdivision": "Seville Parcel 3",
    "assessor_url": "https://mcassessor.maricopa.gov/mcs/?q=99901362&mod=pd",
    "instrument_numbers": [
      "20080200001",
      "20080200002",
      "20190200001",
      "20230200001",
      "20240200001"
    ]
  },
  {
    "apn": "999-02-555",
    "address": "2741 E Palmer St",
    "city": "Gilbert",
    "state": "AZ",
    "zip": "85298",
    "legal_description": "Lot 322, SHAMROCK ESTATES PHASE 2A, according to the plat of record in the office of the County Recorder of Maricopa County, Arizona, recorded in Book 799 of Maps, Page 38",
    "current_owner": "MARTINEZ SOFIA ANDREA",
    "type": "residential",
    "subdivision": "Shamrock Estates Phase 2A",
    "assessor_url": "https://mcassessor.maricopa.gov/mcs/?q=99902555&mod=pd",
    "instrument_numbers": [
      "20160200001",
      "20160200002",
      "20210200001",
      "20210200002",
      "20220200001"
    ]
  },
  {
    "apn": "999-03-411",
    "address": "3594 E Palmer St",
    "city": "Gilbert",
    "state": "AZ",
    "zip": "85298",
    "legal_description": "Lot 38, SEVILLE PARCEL 3, according to the plat of record in the office of the County Recorder of Maricopa County, Arizona, recorded in Book 554 of Maps, Page 19; Affidavit of Correction recorded in Document No. 2001-0849180",
    "current_owner": "DELGADO PROPERTY HOLDINGS LLC",
    "type": "residential",
    "subdivision": "Seville Parcel 3",
    "assessor_url": "https://mcassessor.maricopa.gov/mcs/?q=99903411&mod=pd",
    "instrument_numbers": [
      "20170200001",
      "20170200002",
      "20220200002",
      "20220200003",
      "20220200004"
    ]
  },
  {
    "apn": "999-04-401",
    "address": "3722 E Parkview Ave",
    "city": "Gilbert",
    "state": "AZ",
    "zip": "85298",
    "legal_description": "Lot 56, SEVILLE PARCEL 3, according to the plat of record in the office of the County Recorder of Maricopa County, Arizona, recorded in Book 554 of Maps, Page 19; Affidavit of Correction recorded in Document No. 2001-0849180",
    "current_owner": "BRYANT JAMES T",
    "type": "residential",
    "subdivision": "Seville Parcel 3",
    "assessor_url": "https://mcassessor.maricopa.gov/mcs/?q=99904401&mod=pd",
    "instrument_numbers": [
      "20050200001",
      "20050200002",
      "20220200005",
      "20230200002",
      "20230200003"
    ]
  }
]
